{
    "Description": "The Azure Active Directory (Azure AD) enterprise identity service provides SSO and multi-factor authentication to help protect your users from 99.9 per cent of cybersecurity attacks.",
    "Id": 14183,
    "Name": "Microsoft Azure Active Directory",
    "Version": null,
    "Status": "Approved",
    "Icon": "https://my.cyclr.com/api/ConnectorIcon/14183",
    "Categories": [
        "Developer Tools"
    ],
    "MethodCategories": [
        {
            "Category": "Users",
            "Methods": [
                {
                    "Name": "List User's Group Memberships",
                    "Description": "Retrieves the specified user's group memberships.",
                    "MethodType": "Action"
                },
                {
                    "Name": "List Users",
                    "Description": "Retrieves all users.",
                    "MethodType": "Action"
                },
                {
                    "Name": "Get User",
                    "Description": "Retrieves a single user by ID.",
                    "MethodType": "Action"
                },
                {
                    "Name": "Get User's Manager",
                    "Description": "Retrieves details of a user's manager. If now manager found exits via false path.",
                    "MethodType": "Action"
                },
                {
                    "Name": "List New Users",
                    "Description": "Retrieves all users created since the last time this action was executed.",
                    "MethodType": "Action"
                }
            ]
        },
        {
            "Category": "Groups",
            "Methods": [
                {
                    "Name": "List Groups",
                    "Description": "Retrieves all groups.",
                    "MethodType": "Action"
                },
                {
                    "Name": "List Group Members",
                    "Description": "Retrieves all members of the specified group.",
                    "MethodType": "Action"
                },
                {
                    "Name": "Get Group",
                    "Description": "Retrieves a single group by ID.",
                    "MethodType": "Action"
                }
            ]
        },
        {
            "Category": "Places",
            "Methods": [
                {
                    "Name": "List Rooms",
                    "Description": "Retrieves all rooms in a tenant.",
                    "MethodType": "Action"
                },
                {
                    "Name": "List Room Lists",
                    "Description": "Retrieves all room lists in a tenant.",
                    "MethodType": "Action"
                },
                {
                    "Name": "List Rooms By Room List",
                    "Description": "Retrieves all rooms in the specified room list.",
                    "MethodType": "Action"
                }
            ]
        },
        {
            "Category": "Devices",
            "Methods": [
                {
                    "Name": "List Owned Devices",
                    "Description": "Retrieves devices that are owned by the user.",
                    "MethodType": "Action"
                },
                {
                    "Name": "List Registered Devices",
                    "Description": "Retrieves the user's registered devices.",
                    "MethodType": "Action"
                }
            ]
        },
        {
            "Category": "Organization",
            "Methods": [
                {
                    "Name": "Get Organization",
                    "Description": "Retrieves the properties and relationships of the currently authenticated organization.",
                    "MethodType": "Action"
                }
            ]
        }
    ],
    "MetaTile": null,
    "MetaDescription": null,
    "Screenshot": null,
    "Content": null,
    "WebsiteUrl": null,
    "DocumentationUrl": null,
    "PartnerSetupGuideUrl": "https://docs.cyclr.com/azure-ad-connector"
}