{
    "Description": "Connect with your friends \u00e2\u20ac\u201d and other fascinating people. Get in-the-moment updates on the things that interest you.",
    "Id": 8156,
    "Name": "Twitter",
    "Version": "1.1",
    "Status": "Approved",
    "Icon": "https://my.cyclr.com/api/ConnectorIcon/8156",
    "Categories": [
        "Marketing",
        "Social Media"
    ],
    "MethodCategories": [
        {
            "Category": "Mentions",
            "Methods": [
                {
                    "Name": "Get Mentions",
                    "Description": "Returns the 20 most recent mentions.",
                    "MethodType": "Action"
                }
            ]
        },
        {
            "Category": "Tweets",
            "Methods": [
                {
                    "Name": "Post Tweet",
                    "Description": "Send a tweet.",
                    "MethodType": "Action"
                },
                {
                    "Name": "Search Tweets",
                    "Description": "Returns a collection of relevant Tweets matching a specified query.",
                    "MethodType": "Action"
                }
            ]
        },
        {
            "Category": "Users",
            "Methods": [
                {
                    "Name": "Get User Information",
                    "Description": "Returns a variety of information about the user specified by the Screen Name parameter. ",
                    "MethodType": "Action"
                }
            ]
        }
    ],
    "MetaTile": "Twitter Integration - Social Media Marketing Automation - Cyclr",
    "MetaDescription": "Create your own marketing automation workflows that integrate Twitter with your business applications with Cyclr's drag and drop workflow builder.",
    "Screenshot": null,
    "Content": null,
    "WebsiteUrl": "https://cyclr.com/integrate/twitter",
    "DocumentationUrl": null,
    "PartnerSetupGuideUrl": null
}